pinner/__init__.py
pinner/cli.py
pinner/version.txt
pypinner/__init__.py
pypinner/cli.py
pypinner/version.txt
pypinner-0.0.5.dist-info/DESCRIPTION.rst
pypinner-0.0.5.dist-info/LICENSE.txt
pypinner-0.0.5.dist-info/METADATA
pypinner-0.0.5.dist-info/RECORD
pypinner-0.0.5.dist-info/WHEEL
pypinner-0.0.5.dist-info/entry_points.txt
pypinner-0.0.5.dist-info/metadata.json
pypinner-0.0.5.dist-info/top_level.txt
